{
    "error": "OK",
    "limit": 1,
    "offset": 0,
    "number_of_page_results": 1,
    "number_of_total_results": 1,
    "status_code": 1,
    "results": {
        "abbreviation": "GBA",
        "company": {
            "api_detail_url": "http:\/\/www.giantbomb.com\/api\/company\/3010-90\/",
            "id": 90,
            "name": "Nintendo"
        },
        "deck": "The third platform in the Game Boy line, the Game Boy Advance was offered in a multitude of colors and had three hardware offerings, the sideways Game Boy Advance, the flip Game Boy Advance SP and the tiny Game Boy Advance Micro.",
        "description": "<h2>Overview<\/h2><figure data-align=\"right\" data-img-src=\"http:\/\/static.giantbomb.com\/uploads\/original\/12\/121177\/1705634-810156_gba_logo_super.png\" data-ref-id=\"1300-1705634\" data-size=\"small\" data-ratio=\"0.40042826552463\" data-width=\"467\" data-embed-type=\"image\" style=\"width: 467px\"><a class=\"fluid-height\" style=\"padding-bottom:40.0%\" href=\"http:\/\/static.giantbomb.com\/uploads\/original\/12\/121177\/1705634-810156_gba_logo_super.png\" data-ref-id=\"1300-1705634\"><img alt=\"Game Boy Advance Logo\" src=\"http:\/\/static.giantbomb.com\/uploads\/scale_small\/12\/121177\/1705634-810156_gba_logo_super.png\" srcset=\"http:\/\/static.giantbomb.com\/uploads\/original\/12\/121177\/1705634-810156_gba_logo_super.png 467w, http:\/\/static.giantbomb.com\/uploads\/scale_small\/12\/121177\/1705634-810156_gba_logo_super.png 320w\" sizes=\"(max-width: 320px) 100vw, 320px\" data-width=\"320\"><\/a><figcaption>Game Boy Advance Logo<\/figcaption><\/figure><p>The Game Boy Advance was originally launched in <a href=\"\/japan\/3035-37\/\" data-ref-id=\"3035-37\">Japan<\/a> on March 21, 2001 and then in <a href=\"\/north-america\/3035-1664\/\" data-ref-id=\"3035-1664\">North America<\/a> on June 11. It is the third platform in the <a href=\"\/game-boy\/3045-3\/\" data-ref-id=\"3045-3\">Game Boy<\/a> hand-held line and like it's predecessors, the Game Boy Advance established itself as the leader in the portable market. The Game Boy Advance continued the <a href=\"\/game-boy-color\/3045-57\/\" data-ref-id=\"3045-57\">Game Boy Color<\/a> trend of offering different colors and special branded limited editions. It also established the trend of a periodic hardware redesign (see below), which was carried on with the <a href=\"\/nintendo-ds\/3045-52\/\" data-ref-id=\"3045-52\">Nintendo DS<\/a> and DS Lite. The Game Boy Advance series has had sales of over 81 million worldwide, approx 43 million of which are Game Boy Advance SP units.<\/p><h2>Launch Titles<\/h2><h3>Japan<\/h3><ul><li><a href=\"\/gt-advance-championship-racing\/3030-14360\/\" data-ref-id=\"3030-14360\">Advance GTA<\/a><\/li><li><a href=\"\/castlevania-circle-of-the-moon\/3030-13197\/\" data-ref-id=\"3030-13197\">Akumajo Dracula: Circle of the Moon<\/a><\/li><li><a href=\"\/super-dodge-ball-advance\/3030-13484\/\" data-ref-id=\"3030-13484\">Bakunetsu Dodgeball Fighters<\/a><\/li><li><a href=\"\/boku-wa-koukuu-kansei-an\/3030-13321\/\" data-ref-id=\"3030-13321\">Boku wa Koukuu Kansei-An<\/a><\/li><li><a href=\"\/chuchu-rocket\/3030-13715\/\" data-ref-id=\"3030-13715\">ChuChu Rocket!<\/a><\/li><li><a href=\"\/eztalk-shokyuuhen-16-kan-set\/3030-54207\/\" data-ref-id=\"3030-54207\">EZ-Talk Shokyuuhen 1-6 Kan Set<\/a><\/li><li><a href=\"\/fire-pro-wrestling\/3030-18302\/\" data-ref-id=\"3030-18302\">Fire Pro Wrestling A<\/a><\/li><li><a href=\"\/jleague-pocket\/3030-54206\/\" data-ref-id=\"3030-54206\">J-League Pocket<\/a><\/li><li><a href=\"\/espn-final-round-golf-2002\/3030-22200\/\" data-ref-id=\"3030-22200\">JTO Golf Master: Japan Tour Golf Game<\/a><\/li><li><a href=\"\/kuru-kuru-kururin\/3030-7040\/\" data-ref-id=\"3030-7040\">Kuru Kuru Kururin<\/a><\/li><li><a href=\"\/konami-krazy-racers\/3030-710\/\" data-ref-id=\"3030-710\">Konami Wai Wai Racing Advance<\/a><\/li><li><a href=\"\/momotaro-matsuri\/3030-40218\/\" data-ref-id=\"3030-40218\">Momotaro Matsuri<\/a><\/li><li><a href=\"\/monster-guardians\/3030-54208\/\" data-ref-id=\"3030-54208\">Monster Guardians<\/a><\/li><li><a href=\"\/mr-driller-2\/3030-2514\/\" data-ref-id=\"3030-2514\">Mr. Driller 2<\/a><\/li><li><a href=\"\/napoleon\/3030-21197\/\" data-ref-id=\"3030-21197\">Napoleon<\/a><\/li><li><a href=\"\/pinobee-wings-of-adventure\/3030-6584\/\" data-ref-id=\"3030-6584\">Pinobee no Daibouken<\/a><\/li><li><a href=\"\/power-pro-kun-pocket-3\/3030-43099\/\" data-ref-id=\"3030-43099\">Power Pro-Kun Pocket 3<\/a><\/li><li><a href=\"\/mega-man-battle-network\/3030-8238\/\" data-ref-id=\"3030-8238\">Rockman.EXE<\/a><\/li><li><a href=\"\/silent-hill-play-novel\/3030-19493\/\" data-ref-id=\"3030-19493\">Silent Hill: Play Novel<\/a><\/li><li><a href=\"\/super-mario-advance\/3030-5215\/\" data-ref-id=\"3030-5215\">Super Mario Advance<\/a><\/li><li><a href=\"\/tweety-and-the-magic-gems\/3030-13835\/\" data-ref-id=\"3030-13835\">Tweety no Hearty Party<\/a><\/li><li><a href=\"\/winning-post\/3030-38329\/\" data-ref-id=\"3030-38329\">Winning Post for Game Boy Advance<\/a><\/li><li><a href=\"\/yu-gi-oh-dungeon-dice-monsters\/3030-34915\/\" data-ref-id=\"3030-34915\">Yu-Gi-Oh! Dungeon Dice Monsters<\/a><\/li><li><a href=\"\/top-gear-gt-championship\/3030-36510\/\" data-ref-id=\"3030-36510\">Zen Nihon GT Senshuken<\/a><\/li><\/ul><h3>North America<\/h3><ul><li><a href=\"\/army-men-advance\/3030-10937\/\" data-ref-id=\"3030-10937\">Army Men Advance<\/a><\/li><li><a href=\"\/castlevania-circle-of-the-moon\/3030-13197\/\" data-ref-id=\"3030-13197\">Castlevania: Circle of the Moon<\/a><\/li><li><a href=\"\/chuchu-rocket\/3030-13715\/\" data-ref-id=\"3030-13715\">ChuChu Rocket!<\/a><\/li><li><a href=\"\/earthworm-jim\/3030-11133\/\" data-ref-id=\"3030-11133\">Earthworm Jim<\/a><\/li><li><a href=\"\/f-zero-maximum-velocity\/3030-46\/\" data-ref-id=\"3030-46\">F-Zero: Maximum Velocity<\/a><\/li><li><a href=\"\/fire-pro-wrestling\/3030-18302\/\" data-ref-id=\"3030-18302\">Fire Pro Wrestling<\/a><\/li><li><a href=\"\/gt-advance-championship-racing\/3030-14360\/\" data-ref-id=\"3030-14360\">GT Advance Championship Racing<\/a><\/li><li><a href=\"\/iridion-3d\/3030-69\/\" data-ref-id=\"3030-69\">Iridion 3D<\/a><\/li><li><a href=\"\/konami-krazy-racers\/3030-710\/\" data-ref-id=\"3030-710\">Konami Krazy Racers<\/a><\/li><li><a href=\"\/namco-museum\/3030-32352\/\" data-ref-id=\"3030-32352\">Namco Museum<\/a><\/li><li><a href=\"\/pinobee-wings-of-adventure\/3030-6584\/\" data-ref-id=\"3030-6584\">Pinobee: Wings of Adventure<\/a><\/li><li><a href=\"\/pitfall-the-mayan-adventure\/3030-9331\/\" data-ref-id=\"3030-9331\">Pitfall: The Mayan Adventure<\/a><\/li><li><a href=\"\/rayman\/3030-18473\/\" data-ref-id=\"3030-18473\">Rayman Advance<\/a><\/li><li><a href=\"\/ready-2-rumble-boxing-round-2\/3030-11649\/\" data-ref-id=\"3030-11649\">Ready 2 Rumble Boxing: Round 2<\/a><\/li><li><a href=\"\/super-dodge-ball-advance\/3030-13484\/\" data-ref-id=\"3030-13484\">Super Dodge Ball Advance<\/a><\/li><li><a href=\"\/super-mario-advance\/3030-5215\/\" data-ref-id=\"3030-5215\">Super Mario Advance<\/a><\/li><li><a href=\"\/tony-hawks-pro-skater-2\/3030-990\/\" data-ref-id=\"3030-990\">Tony Hawk's Pro Skater 2<\/a><\/li><\/ul><h3>Europe<\/h3><ul><li><a href=\"\/f-zero-maximum-velocity\/3030-46\/\" data-ref-id=\"3030-46\">F-Zero: Maximum Velocity<\/a><\/li><li><a href=\"\/top-gear-gt-championship\/3030-36510\/\" data-ref-id=\"3030-36510\">Top Gear GT Championship<\/a><\/li><li><a href=\"\/konami-krazy-racers\/3030-710\/\" data-ref-id=\"3030-710\">Konami Krazy Racers<\/a><\/li><li><a href=\"\/kuru-kuru-kururin\/3030-7040\/\" data-ref-id=\"3030-7040\">Kuru Kuru Kururin<\/a><\/li><li><a href=\"\/ready-2-rumble-boxing-round-2\/3030-11649\/\" data-ref-id=\"3030-11649\">Ready 2 Rumble Boxing Round 2<\/a><\/li><li><a href=\"\/super-mario-advance\/3030-5215\/\" data-ref-id=\"3030-5215\">Super Mario Advance<\/a><\/li><li><a href=\"\/tony-hawks-pro-skater-2\/3030-990\/\" data-ref-id=\"3030-990\">Tony Hawk's Pro Skater 2<\/a><\/li><li><a href=\"\/tweety-and-the-magic-gems\/3030-13835\/\" data-ref-id=\"3030-13835\">Tweety and The Magic Jewel<\/a><\/li><li><a href=\"\/castlevania-circle-of-the-moon\/3030-13197\/\" data-ref-id=\"3030-13197\">Castlevania: Circle of the Moon<\/a><\/li><\/ul><h2>Games<\/h2><figure data-align=\"right\" data-img-src=\"http:\/\/static.giantbomb.com\/uploads\/original\/0\/7465\/873717-6a00d83452033569e200e54f27386f8834_800wi.jpg\" data-ref-id=\"1300-873717\" data-size=\"small\" data-ratio=\"0.75333333333333\" data-width=\"300\" data-embed-type=\"image\" style=\"width: 300px\"><a class=\"fluid-height\" style=\"padding-bottom:75.3%\" href=\"http:\/\/static.giantbomb.com\/uploads\/original\/0\/7465\/873717-6a00d83452033569e200e54f27386f8834_800wi.jpg\" data-ref-id=\"1300-873717\"><img alt=\"A typical Game Boy Advance cartridge.\" src=\"http:\/\/static.giantbomb.com\/uploads\/original\/0\/7465\/873717-6a00d83452033569e200e54f27386f8834_800wi.jpg\" srcset=\"http:\/\/static.giantbomb.com\/uploads\/original\/0\/7465\/873717-6a00d83452033569e200e54f27386f8834_800wi.jpg 300w\" sizes=\"(max-width: 300px) 100vw, 300px\" data-width=\"300\"><\/a><figcaption>A typical Game Boy Advance cartridge.<\/figcaption><\/figure><p>The Game Boy Advance's hardware was very similar to the <a href=\"\/snes\/3045-9\/\" data-ref-id=\"3045-9\">SNES<\/a>'s, which made it perfect for sprite-based games. It had many ports of SNES titles, including a large number of RPGs. As well as being known for its SNES remakes and great original content a lot of original <a href=\"\/nes\/3045-21\/\" data-ref-id=\"3045-21\">NES<\/a> games were made available to play on the move thanks to the <a href=\"\/classic-nes-series\/3015-3653\/\" data-ref-id=\"3015-3653\">NES Classic's Series<\/a>. The Game Boy Advance is regarded as an incredibly popular console among old school gamers and many call it <a href=\"\/nintendo\/3010-90\/\" data-ref-id=\"3010-90\">Nintendo's<\/a> best handheld in terms of games. The last game to be release for the Game Boy Advance was <a href=\"\/samurai-deeper-kyo\/3030-28897\/\" data-ref-id=\"3030-28897\">Samurai Deeper Kyo<\/a> which was released on February 12, 2008 in North America. As of March, 2009 there has been over 377 million GBA games sold worldwide.<\/p><h3>Best Selling Games Worldwide<\/h3><ol><li><a href=\"\/pokemon-rubysapphire\/3030-10122\/\" data-ref-id=\"3030-10122\"><i>Pok\u00e9mon Ruby<\/i>\/<i>Sapphire<\/i><\/a> (13 million)<\/li><li><a href=\"\/pokemon-fireredleafgreen\/3030-14522\/\" data-ref-id=\"3030-14522\"><i>Pok\u00e9mon FireRed<\/i>\/<i>LeafGreen<\/i><\/a> (11.82 million)<\/li><li><i>Pok\u00e9mon Emerald<\/i> (6.32 million)<\/li><li><i>Super Mario World: Super Mario Advance 2<\/i> (4.179 million approx)<\/li><li><i>Super Mario Advance<\/i> (3.938 million approx)<\/li><li><a href=\"\/mario-kart-super-circuit\/3030-16769\/\" data-ref-id=\"3030-16769\"><i>Mario Kart: Super Circuit<\/i><\/a> (3.768 million approx)<\/li><li><a href=\"\/super-mario-bros-3-super-mario-advance-4\/3030-20748\/\" data-ref-id=\"3030-20748\"><i>Super Mario Advance 4: Super Mario Bros. 3<\/i><\/a> (3.698 million approx)<\/li><li><i>Namco Museum<\/i> (2.96 million in US)<\/li><li><i>Pok\u00e9mon Pinball: Ruby &amp; Sapphire<\/i> (2.5 million)<\/li><li><i>Pok\u00e9mon Mystery Dungeon: Red Rescue Team<\/i> (2.2 million)<\/li><\/ol><h2>Hardware Revisions<\/h2><p>There were three different models offered during the lifespan of the Game Boy Advance.<\/p><table><tbody><tr><th>Game Boy Advance (GBA)<\/th><\/tr><tr><td>The original Game Boy Advance was released with a horizontal design. This model is backwards compatible with games for the Game Boy and Game Boy Color. Many gamers complained that the screen was not bright enough on this model and many third party lighting accessories were developed, this issue was fixed in the next iteration.<\/td><td><figure data-align=\"left\" data-img-src=\"http:\/\/static.giantbomb.com\/uploads\/original\/0\/9566\/395908-nintendo_game_boy_advance.jpeg\" data-ref-id=\"1300-395908\" data-size=\"small\" data-ratio=\"0.8\" data-width=\"450\" data-embed-type=\"image\" style=\"width: 450px\"><a class=\"fluid-height\" style=\"padding-bottom:80.0%\" href=\"http:\/\/static.giantbomb.com\/uploads\/original\/0\/9566\/395908-nintendo_game_boy_advance.jpeg\" data-ref-id=\"1300-395908\"><img alt=\"Indigo\" src=\"data:image\/gif;base64,R0lGODlhAQABAAAAACH5BAEKAAEALAAAAAABAAEAAAICTAEAOw==\" sizes=\"(max-width: 320px) 100vw, 320px\" data-width=\"320\" class=\"js-lazy-load-image\" data-src=\"http:\/\/static.giantbomb.com\/uploads\/scale_small\/0\/9566\/395908-nintendo_game_boy_advance.jpeg\" data-srcset=\"http:\/\/static.giantbomb.com\/uploads\/original\/0\/9566\/395908-nintendo_game_boy_advance.jpeg 450w, http:\/\/static.giantbomb.com\/uploads\/scale_small\/0\/9566\/395908-nintendo_game_boy_advance.jpeg 320w\"><noscript><img alt=\"Indigo\" src=\"http:\/\/static.giantbomb.com\/uploads\/scale_small\/0\/9566\/395908-nintendo_game_boy_advance.jpeg\" srcset=\"http:\/\/static.giantbomb.com\/uploads\/original\/0\/9566\/395908-nintendo_game_boy_advance.jpeg 450w, http:\/\/static.giantbomb.com\/uploads\/scale_small\/0\/9566\/395908-nintendo_game_boy_advance.jpeg 320w\" sizes=\"(max-width: 320px) 100vw, 320px\" data-width=\"320\"><\/noscript><\/a><figcaption>Indigo<\/figcaption><\/figure><\/td><\/tr><tr><td><h3>Hardware Specs<\/h3><ul><li>CPU: 32-bit RISC CPU with embedded memory<\/li><\/ul><ul><li>Screen: 2.9\" Reflective TFT Color LCD<\/li><li>Display Size: 1.6\" by 2.4\" (40.8 by 61.2 mm)<\/li><li>Resolution: 240 x 160 pixels<\/li><li>Colors: 512 simultaneous colors from a palette of 32,768<\/li><li>Size: 3.2 by 5.6 by 1 inch (82 by 144.5 by 24.5 mm)<\/li><li>Weight: Approximately 5 ounces (140 grams)<\/li><li>Power Supply: 2 AA alkaline batteries<\/li><li>Battery Life: Approximately 15 hours continuous play<\/li><\/ul><\/td><td><ul><li>Launch Date: June 11, 2001<\/li><li>Launch Price: $149.99<\/li><\/ul><\/td><\/tr><\/tbody><\/table><table><tbody><tr><th>Game Boy Advance SP<\/th><\/tr><tr><td>The Game Boy Advance SP not only saw a major change with its flip design, but also added a built-in (but removeable, with tools) rechargeable battery and front mounted light. Like the original GBA, the SP is backwards compatible with all Game Boy and Game Boy Color games. This version did not have a standard headphone jack, and users dissatisfied by the small built-in speaker needed either proprietary Nintendo headphones or an adapter. In September of 2005, a back-lit model of the SP was released. This version of the hardware is recognizable by the model number AGS-101.<\/td><td><figure data-align=\"left\" data-img-src=\"http:\/\/static.giantbomb.com\/uploads\/original\/0\/8272\/1352103-gbasp_famicom.jpg\" data-ref-id=\"1300-1352103\" data-size=\"small\" data-ratio=\"1.0933333333333\" data-width=\"300\" data-embed-type=\"image\" style=\"width: 300px\"><a class=\"fluid-height\" style=\"padding-bottom:109.3%\" href=\"http:\/\/static.giantbomb.com\/uploads\/original\/0\/8272\/1352103-gbasp_famicom.jpg\" data-ref-id=\"1300-1352103\"><img alt=\"Famicom version\" src=\"data:image\/gif;base64,R0lGODlhAQABAAAAACH5BAEKAAEALAAAAAABAAEAAAICTAEAOw==\" sizes=\"(max-width: 300px) 100vw, 300px\" data-width=\"300\" class=\"js-lazy-load-image\" data-src=\"http:\/\/static.giantbomb.com\/uploads\/original\/0\/8272\/1352103-gbasp_famicom.jpg\" data-srcset=\"http:\/\/static.giantbomb.com\/uploads\/original\/0\/8272\/1352103-gbasp_famicom.jpg 300w\"><noscript><img alt=\"Famicom version\" src=\"http:\/\/static.giantbomb.com\/uploads\/original\/0\/8272\/1352103-gbasp_famicom.jpg\" srcset=\"http:\/\/static.giantbomb.com\/uploads\/original\/0\/8272\/1352103-gbasp_famicom.jpg 300w\" sizes=\"(max-width: 300px) 100vw, 300px\" data-width=\"300\"><\/noscript><\/a><figcaption>Famicom version<\/figcaption><\/figure><\/td><\/tr><tr><td><h3>Hardware Specs<\/h3><ul><li>CPU: 32-bit RISC-CPU with embedded memory<\/li><li>Screen: 2.9\" Reflective TFT Color LCD Display Size: 1.61\" x 2.41\"<\/li><li>Resolution: 240 x 160 pixels Color:<\/li><li>Simultaneously display more than 32,000 colors<\/li><li>Size (Closed): Height 3.33 inches, width 3.23 inches, depth 0.96 inches<\/li><li>Weight: Approximately 5 ounces (140 grams)<\/li><li>Power Supply: Lithium-Ion rechargeable battery<\/li><li>Battery Life: Approximately 10 hours of continuous play with light, 18 hours without light<\/li><\/ul><\/td><td><ul><li>Launch Date: March 23, 2003<\/li><li>Launch Price: $ 99.99<\/li><\/ul><\/td><\/tr><\/tbody><\/table><table><tbody><tr><th>Game Boy Micro<\/th><\/tr><tr><td>Tiny in size, the third design borrowed from the then-popular cell phone trend of having interchangeable face-plates. Featuring a brighter screen than the SP (with 5 levels of adjustable brightness) and a standard headphone jack (found at the bottom of the unit), but with an external port unique to the Micro which did not accept a standard GBA link cable (though a cable exclusive to the micro was released) and able to play Game Boy Advance games only, this version of the platform never achieved the success of the previous two versions.<\/td><td><figure data-align=\"left\" data-img-src=\"http:\/\/static.giantbomb.com\/uploads\/original\/0\/9983\/680978-micro.jpg\" data-ref-id=\"1300-680978\" data-size=\"small\" data-ratio=\"0.61806981519507\" data-width=\"487\" data-embed-type=\"image\" style=\"width: 487px\"><a class=\"fluid-height\" style=\"padding-bottom:61.8%\" href=\"http:\/\/static.giantbomb.com\/uploads\/original\/0\/9983\/680978-micro.jpg\" data-ref-id=\"1300-680978\"><img alt=\"No Caption Provided\" src=\"data:image\/gif;base64,R0lGODlhAQABAAAAACH5BAEKAAEALAAAAAABAAEAAAICTAEAOw==\" sizes=\"(max-width: 320px) 100vw, 320px\" data-width=\"320\" class=\"js-lazy-load-image\" data-src=\"http:\/\/static.giantbomb.com\/uploads\/scale_small\/0\/9983\/680978-micro.jpg\" data-srcset=\"http:\/\/static.giantbomb.com\/uploads\/original\/0\/9983\/680978-micro.jpg 487w, http:\/\/static.giantbomb.com\/uploads\/scale_medium\/0\/9983\/680978-micro.jpg 480w, http:\/\/static.giantbomb.com\/uploads\/scale_small\/0\/9983\/680978-micro.jpg 320w\"><noscript><img alt=\"No Caption Provided\" src=\"http:\/\/static.giantbomb.com\/uploads\/scale_small\/0\/9983\/680978-micro.jpg\" srcset=\"http:\/\/static.giantbomb.com\/uploads\/original\/0\/9983\/680978-micro.jpg 487w, http:\/\/static.giantbomb.com\/uploads\/scale_medium\/0\/9983\/680978-micro.jpg 480w, http:\/\/static.giantbomb.com\/uploads\/scale_small\/0\/9983\/680978-micro.jpg 320w\" sizes=\"(max-width: 320px) 100vw, 320px\" data-width=\"320\"><\/noscript><\/a><\/figure><\/td><\/tr><tr><td><h3>Hardware Specs<\/h3><ul><li>CPU: 32-bit RISC-CPU (16.78 MHz)<\/li><li>Screen: 2-inch diagonal screen TFT<\/li><li>Display Size: 1.61\" x 2.41\"<\/li><li>Resolution: 240 x 160 pixels<\/li><li>Color: 512 out of a maximum 32,000 colors<\/li><li>Size: Measures 4 by 0.7 by 2 inches<\/li><li>Weight: Approximately 2.8 ounces<\/li><li>Power Supply: Lithium-Ion rechargeable battery<\/li><li>Battery Life: Approximately 6 to 10 hours, depending on brightness level.<\/li><\/ul><\/td><td><ul><li>Launch Date: Sept 19, 2005<\/li><li>Launch Price: $99.99<\/li><\/ul><\/td><\/tr><\/tbody><\/table><h2>Official Nintendo Accessories<\/h2><p>Many accessories were created for the Game Boy Advance line.<\/p><table data-max-width=\"true\"><thead><tr><th scope=\"col\">Game Link Cable<\/th><th scope=\"col\"> <\/th><\/tr><\/thead><tbody><tr><td>This 4-port cable allowed between 2 and 4 Game Boy Advance units to communicate for multiplayer games or to share or trade data. The game that is best known for its use of this accessory is <a href=\"\/the-legend-of-zelda-a-link-to-the-past-four-swords\/3030-35064\/\" data-ref-id=\"3030-35064\">The Legend of Zelda: A Link to the Past &amp; Four Swords<\/a>, which is the GBA remake of the SNES classic.<\/td><td><figure data-align=\"right\" data-size=\"medium\" data-img-src=\"http:\/\/static.giantbomb.com\/uploads\/original\/16\/164924\/2486361-gba_link_cable_en.jpg\" data-ref-id=\"1300-2486361\" data-ratio=\"0.8\" data-width=\"155\" data-embed-type=\"image\" style=\"width: 155px\"><a class=\"fluid-height\" style=\"padding-bottom:80.0%\" href=\"http:\/\/static.giantbomb.com\/uploads\/original\/16\/164924\/2486361-gba_link_cable_en.jpg\" data-ref-id=\"1300-2486361\"><img alt=\"No Caption Provided\" src=\"data:image\/gif;base64,R0lGODlhAQABAAAAACH5BAEKAAEALAAAAAABAAEAAAICTAEAOw==\" sizes=\"(max-width: 155px) 100vw, 155px\" data-width=\"155\" class=\"js-lazy-load-image\" data-src=\"http:\/\/static.giantbomb.com\/uploads\/original\/16\/164924\/2486361-gba_link_cable_en.jpg\" data-srcset=\"http:\/\/static.giantbomb.com\/uploads\/original\/16\/164924\/2486361-gba_link_cable_en.jpg 155w\"><noscript><img alt=\"No Caption Provided\" src=\"http:\/\/static.giantbomb.com\/uploads\/original\/16\/164924\/2486361-gba_link_cable_en.jpg\" srcset=\"http:\/\/static.giantbomb.com\/uploads\/original\/16\/164924\/2486361-gba_link_cable_en.jpg 155w\" sizes=\"(max-width: 155px) 100vw, 155px\" data-width=\"155\"><\/noscript><\/a><\/figure><\/td><\/tr><\/tbody><\/table><table data-max-width=\"true\"><thead><tr><th scope=\"col\">Nintendo Gamecube Game Boy Advance Link Cable<\/th><th scope=\"col\"> <\/th><\/tr><\/thead><tbody><tr><td>This cable allowed you to use your GBA with certain Gamecube games, such as <a href=\"\/the-legend-of-zelda-four-swords-adventures\/3030-7856\/\" data-ref-id=\"3030-7856\">The Legend of Zelda: Four Swords Adventures<\/a>, <a href=\"\/pac-man-vs\/3030-12338\/\" data-ref-id=\"3030-12338\">Pac-Man VS<\/a> and <a href=\"\/\/\/\">Final Fantasy: Crystal Chronicles<\/a>, as a controller (with screen!) for your Gamecube. Some other games also used the accessory for side featrures, for example being able to travel to<\/td><td> <\/td><\/tr><\/tbody><\/table><table data-max-width=\"true\"><thead><tr><th scope=\"col\">Game Boy Wireless Adapter<\/th><th scope=\"col\"> <\/th><\/tr><\/thead><tbody><tr><td>The wireless adapter was a great alternative to the wired Game Link cable, but only worked with certain games designed specifically for it. As it was released relatively late in the handhelds life less than 20 games supported it the most pominent tat offered support was <a href=\"\/pokemon-fireredleafgreen\/3030-14522\/\" data-ref-id=\"3030-14522\">Pokemon FireRed\/LeafGreen<\/a> which had the adapter included with the game.<\/td><td> <\/td><\/tr><\/tbody><\/table><table data-max-width=\"true\"><thead><tr><th scope=\"col\"><a href=\"\/e-reader\/3015-3782\/\" data-ref-id=\"3015-3782\">e-Reader<\/a><\/th><th scope=\"col\"> <\/th><\/tr><\/thead><tbody><tr><td>This optical scanner was released in 2001 and co-created with Olympus Optical, Ltd. It worked with specially printed dot-patterned cards which could be used to unlock bonus content in games, most notably <a href=\"\/super-mario-bros-3-super-mario-advance-4\/3030-20748\/\" data-ref-id=\"3030-20748\">Super Mario Bros. 3: Super Mario Advance 4<\/a> (which had the most ambitious e-Reader release of all, with multiple packs of cards adding items, levels, and even \"professional\" replays), or to play entire games, especially retro titles like the <a href=\"\/game-watch\/3025-1183\/\" data-ref-id=\"3025-1183\">Game and Watch<\/a> series, or Nintendo Arcade Classics, like the original <a href=\"\/donkey-kong\/3030-311\/\" data-ref-id=\"3030-311\">Donkey Kong<\/a>. The device was inserted into the cartridge slot of the Game Boy Advance, (shown here to the right), and featured a pass-through port to allow connection of multiple Game Boy Advance units using the standard Game Link Cable. The e-Reader served as a bootable cartridge, and had onboard memory to store one game at a time, but for most other features more than one GBA was required, since there was no other way for data to be transferred to a game cartridge, severely limiting its usefulness.<\/td><td><figure data-align=\"right\" data-size=\"small\" data-img-src=\"http:\/\/static.giantbomb.com\/uploads\/original\/0\/7465\/1124594-gba_e_reader.jpg\" data-ref-id=\"1300-1124594\" data-ratio=\"0.7\" data-width=\"400\" data-embed-type=\"image\" style=\"width: 400px\"><a class=\"fluid-height\" style=\"padding-bottom:70.0%\" href=\"http:\/\/static.giantbomb.com\/uploads\/original\/0\/7465\/1124594-gba_e_reader.jpg\" data-ref-id=\"1300-1124594\"><img alt=\"No Caption Provided\" src=\"data:image\/gif;base64,R0lGODlhAQABAAAAACH5BAEKAAEALAAAAAABAAEAAAICTAEAOw==\" sizes=\"(max-width: 320px) 100vw, 320px\" data-width=\"320\" class=\"js-lazy-load-image\" data-src=\"http:\/\/static.giantbomb.com\/uploads\/scale_small\/0\/7465\/1124594-gba_e_reader.jpg\" data-srcset=\"http:\/\/static.giantbomb.com\/uploads\/original\/0\/7465\/1124594-gba_e_reader.jpg 400w, http:\/\/static.giantbomb.com\/uploads\/scale_small\/0\/7465\/1124594-gba_e_reader.jpg 320w\"><noscript><img alt=\"No Caption Provided\" src=\"http:\/\/static.giantbomb.com\/uploads\/scale_small\/0\/7465\/1124594-gba_e_reader.jpg\" srcset=\"http:\/\/static.giantbomb.com\/uploads\/original\/0\/7465\/1124594-gba_e_reader.jpg 400w, http:\/\/static.giantbomb.com\/uploads\/scale_small\/0\/7465\/1124594-gba_e_reader.jpg 320w\" sizes=\"(max-width: 320px) 100vw, 320px\" data-width=\"320\"><\/noscript><\/a><\/figure><p> <\/p><\/td><\/tr><\/tbody><\/table><table data-max-width=\"true\"><thead><tr><th scope=\"col\">Game Boy Advance SP Headphone Jack Adapter<\/th><th scope=\"col\"> <\/th><\/tr><\/thead><tbody><tr><td>This short cable connected to the charging port of the SP and allowed the user to connect a standard 3.5mm headphone jack instead of the charger. Many third parties improved on this design by allowing both the headphone jack and the charger to be used simultaneously.<\/td><td> <\/td><\/tr><\/tbody><\/table><table data-max-width=\"true\"><thead><tr><th scope=\"col\">Game Boy Player<\/th><th scope=\"col\"> <\/th><\/tr><\/thead><tbody><tr><td>This device allowed you to play GBA games on your television by connecting it to your <a href=\"\/gamecube\/3045-23\/\" data-ref-id=\"3045-23\">GameCube<\/a>. The device installed semi-permanently to the bottom of the Gamecube and booted with a standard Gamecube disc. The Game Boy Advance cartridges were inserted in the front of the device, visible in the center of the bottom left-hand side of the picture (right).<\/td><td><figure data-align=\"right\" data-size=\"medium\" data-img-src=\"http:\/\/static.giantbomb.com\/uploads\/original\/0\/9983\/680979-player.jpg\" data-ref-id=\"1300-680979\" data-ratio=\"0.75641025641026\" data-width=\"546\" data-embed-type=\"image\" style=\"width: 546px\"><a class=\"fluid-height\" style=\"padding-bottom:75.6%\" href=\"http:\/\/static.giantbomb.com\/uploads\/original\/0\/9983\/680979-player.jpg\" data-ref-id=\"1300-680979\"><img alt=\"No Caption Provided\" src=\"data:image\/gif;base64,R0lGODlhAQABAAAAACH5BAEKAAEALAAAAAABAAEAAAICTAEAOw==\" sizes=\"(max-width: 480px) 100vw, 480px\" data-width=\"480\" class=\"js-lazy-load-image\" data-src=\"http:\/\/static.giantbomb.com\/uploads\/scale_medium\/0\/9983\/680979-player.jpg\" data-srcset=\"http:\/\/static.giantbomb.com\/uploads\/original\/0\/9983\/680979-player.jpg 546w, http:\/\/static.giantbomb.com\/uploads\/scale_medium\/0\/9983\/680979-player.jpg 480w\"><noscript><img alt=\"No Caption Provided\" src=\"http:\/\/static.giantbomb.com\/uploads\/scale_medium\/0\/9983\/680979-player.jpg\" srcset=\"http:\/\/static.giantbomb.com\/uploads\/original\/0\/9983\/680979-player.jpg 546w, http:\/\/static.giantbomb.com\/uploads\/scale_medium\/0\/9983\/680979-player.jpg 480w\" sizes=\"(max-width: 480px) 100vw, 480px\" data-width=\"480\"><\/noscript><\/a><\/figure><p> <\/p><\/td><\/tr><\/tbody><\/table>",
        "id": 4,
        "image": {
            "icon_url": "http:\/\/www.giantbomb.com\/api\/image\/square_avatar\/2121789-gba.png",
            "medium_url": "http:\/\/www.giantbomb.com\/api\/image\/scale_medium\/2121789-gba.png",
            "screen_url": "http:\/\/www.giantbomb.com\/api\/image\/screen_medium\/2121789-gba.png",
            "small_url": "http:\/\/www.giantbomb.com\/api\/image\/scale_small\/2121789-gba.png",
            "super_url": "http:\/\/www.giantbomb.com\/api\/image\/scale_large\/2121789-gba.png",
            "thumb_url": "http:\/\/www.giantbomb.com\/api\/image\/scale_avatar\/2121789-gba.png",
            "tiny_url": "http:\/\/www.giantbomb.com\/api\/image\/square_mini\/2121789-gba.png"
        },
        "install_base": "81440000",
        "name": "Game Boy Advance",
        "online_support": false,
        "original_price": "100.00",
        "release_date": "2001-03-21 00:00:00",
        "site_detail_url": "http:\/\/www.giantbomb.com\/game-boy-advance\/3045-4\/"
    },
    "version": "0"
}